MANIFEST.in
setup.py
psdash/__init__.py
psdash/helpers.py
psdash/log.py
psdash/net.py
psdash/node.py
psdash/run.py
psdash/web.py
psdash.egg-info/PKG-INFO
psdash.egg-info/SOURCES.txt
psdash.egg-info/dependency_links.txt
psdash.egg-info/entry_points.txt
psdash.egg-info/not-zip-safe
psdash.egg-info/requires.txt
psdash.egg-info/top_level.txt
psdash/static/css/bootstrap-theme.min.css
psdash/static/css/bootstrap.min.css
psdash/static/css/psdash.css
psdash/static/fonts/glyphicons-halflings-regular.eot
psdash/static/fonts/glyphicons-halflings-regular.svg
psdash/static/fonts/glyphicons-halflings-regular.ttf
psdash/static/fonts/glyphicons-halflings-regular.woff
psdash/static/js/bootstrap.min.js
psdash/static/js/jquery.min.js
psdash/static/js/psdash.js
psdash/templates/base.html
psdash/templates/disks.html
psdash/templates/error.html
psdash/templates/index.html
psdash/templates/log.html
psdash/templates/logs.html
psdash/templates/network.html
psdash/templates/process.html
psdash/templates/processes.html
psdash/templates/process/children.html
psdash/templates/process/connections.html
psdash/templates/process/environment.html
psdash/templates/process/files.html
psdash/templates/process/limits.html
psdash/templates/process/memory.html
psdash/templates/process/overview.html
psdash/templates/process/threads.html