Metadata-Version: 1.1
Name: psdash
Version: 0.6.1
Summary: Linux system information web dashboard
Home-page: https://github.com/Jahaja/psdash
Author: Joakim Hamrén
Author-email: joakim.hamren@gmail.com
License: CC0
Keywords: linux web dashboard
Platform: UNKNOWN
Classifier: Topic :: System :: Monitoring
Classifier: Topic :: System :: Logging
Classifier: Topic :: System :: Networking :: Monitoring
Classifier: Development Status :: 4 - Beta
Classifier: Operating System :: POSIX :: Linux
Classifier: Programming Language :: Python
Classifier: License :: Public Domain
Classifier: Intended Audience :: Developers
Classifier: Intended Audience :: System Administrators
